slidge/__init__.py
slidge/__main__.py
slidge/main.py
slidge/migration.py
slidge/py.typed
slidge/command/__init__.py
slidge/command/adhoc.py
slidge/command/admin.py
slidge/command/base.py
slidge/command/categories.py
slidge/command/chat_command.py
slidge/command/register.py
slidge/command/user.py
slidge/contact/__init__.py
slidge/contact/contact.py
slidge/contact/roster.py
slidge/core/__init__.py
slidge/core/config.py
slidge/core/gateway.py
slidge/core/pubsub.py
slidge/core/session.py
slidge/core/dispatcher/__init__.py
slidge/core/dispatcher/caps.py
slidge/core/dispatcher/disco.py
slidge/core/dispatcher/presence.py
slidge/core/dispatcher/registration.py
slidge/core/dispatcher/search.py
slidge/core/dispatcher/session_dispatcher.py
slidge/core/dispatcher/util.py
slidge/core/dispatcher/vcard.py
slidge/core/dispatcher/message/__init__.py
slidge/core/dispatcher/message/chat_state.py
slidge/core/dispatcher/message/marker.py
slidge/core/dispatcher/message/message.py
slidge/core/dispatcher/muc/__init__.py
slidge/core/dispatcher/muc/admin.py
slidge/core/dispatcher/muc/mam.py
slidge/core/dispatcher/muc/misc.py
slidge/core/dispatcher/muc/owner.py
slidge/core/dispatcher/muc/ping.py
slidge/core/mixins/__init__.py
slidge/core/mixins/attachment.py
slidge/core/mixins/avatar.py
slidge/core/mixins/base.py
slidge/core/mixins/db.py
slidge/core/mixins/disco.py
slidge/core/mixins/message.py
slidge/core/mixins/message_maker.py
slidge/core/mixins/message_text.py
slidge/core/mixins/presence.py
slidge/core/mixins/recipient.py
slidge/db/__init__.py
slidge/db/avatar.py
slidge/db/meta.py
slidge/db/models.py
slidge/db/store.py
slidge/db/alembic/__init__.py
slidge/db/alembic/env.py
slidge/db/alembic/script.py.mako
slidge/db/alembic/versions/259a1b71eadf_add_origin_group_id_table.py
slidge/db/alembic/versions/805fdc0bf984_add_unique_constraint_for_occupant_id.py
slidge/db/alembic/versions/86d980dbb426_add_displayed_by_user_column_to_.py
slidge-0.3.6.dist-info/licenses/LICENSE
slidge-0.3.6.dist-info/METADATA
slidge-0.3.6.dist-info/WHEEL
slidge-0.3.6.dist-info/entry_points.txt
slidge-0.3.6.dist-info/top_level.txt
slidge-0.3.6.dist-info/RECORD
