Metadata-Version: 2.4
Name: slidge
Version: 0.3.6
Summary: XMPP bridging framework
Author-email: Nicolas Cedilnik <nicoco@nicoco.fr>
License-Expression: AGPL-3.0-or-later
Project-URL: Homepage, https://codeberg.org/slidge/
Project-URL: Issues, https://codeberg.org/slidge/slidge/issues
Project-URL: Repository, https://codeberg.org/slidge/slidge/
Project-URL: Chat room, https://conference.nicoco.fr:5281/muc_log/slidge/
Project-URL: Documentation, https://slidge.im/docs/slidge/main
Project-URL: changelog, https://codeberg.org/slidge/slidge/releases
Keywords: xmpp,gateway,bridge,instant messaging
Classifier: Topic :: Internet :: XMPP
Classifier: Topic :: Software Development :: Libraries :: Python Modules
Requires-Python: >=3.11
License-File: LICENSE
Requires-Dist: aiohttp[speedups]<4,>=3.11.11
Requires-Dist: alembic<2,>=1.14.0
Requires-Dist: configargparse<2,>=1.7
Requires-Dist: defusedxml>=0.7.1
Requires-Dist: pillow<12,>=11.0.0
Requires-Dist: python-magic<0.5,>=0.4.27
Requires-Dist: qrcode<9,>=8.0
Requires-Dist: slixmpp<1.13.0,>=1.12.0
Requires-Dist: sqlalchemy<3,>=2
Requires-Dist: thumbhash>=0.1.2
Provides-Extra: lottie
Requires-Dist: rlottie-python~=1.3.8; extra == "lottie"
Dynamic: license-file
